mistygrind
