Metadata-Version: 1.1
Name: mistygrind
Version: 0.2.1
Summary: a tool for static analysis of Misty skills and offboard Misty REST API clients
Home-page: https://github.com/rerobots/mistygrind
Author: mistygrind contributors
Author-email: q@rerobots.net
License: Apache-2.0
Platform: UNKNOWN
Classifier: License :: OSI Approved :: Apache Software License
Classifier: Development Status :: 4 - Beta
Classifier: Programming Language :: Python :: 3
Classifier: Programming Language :: Python :: 3.5
Classifier: Programming Language :: Python :: 3.6
Classifier: Programming Language :: Python :: 3.7
Classifier: Programming Language :: Python :: 3.8
